{"api_event_map.md":"19cf3371","api_index.md":"14784599","api_message.md":"bd59cab3","guide_deploy.md":"b1cf41e8","guide_decorator.md":"5ad70534","api_bot.md":"1eb18815","api_service-router.md":"97cfd7ce","api_session.md":"d3df1ce7","api_context.md":"9cd0acdb","guide_config.md":"11f307de","api_command.md":"44363585","api_adapter.md":"acc318f4","api_render-element.md":"434a7f3e","api_render-template.md":"870aec86","api_service-koa.md":"99fc8f17","api_service-server.md":"bdc98444","api_zhin.md":"bb0c1ae1","config_adapter-icqq.md":"baa25ab6","config_adapter-onebot.md":"c7eb11fc","config_built-plugin.md":"017f6c60","config_common.md":"137d0902","guide_bot.md":"8b5a3094","guide_command.md":"073a2b04","guide_prompt.md":"2bc90ffa","api_render-component.md":"6c7ab63f","guide_repeater.md":"60bffaa5","api_service.md":"887eab04","guide_plugin.md":"536c0937","guide_component.md":"2b15eedd","guide_prepare.md":"9dd23d1f","index.md":"fdb0dcfe","guide_start.md":"06723296"}
