{"api_index.md":"aeb4bcba","api_command.md":"96bf488b","api_context.md":"dca159c8","api_message.md":"f2cb48b0","api_event_map.md":"29625008","api_render-component.md":"8ea74de4","api_bot.md":"ec90089c","api_adapter.md":"e6797ad4","api_render-element.md":"c87fed4e","api_render-template.md":"27231f06","api_service-server.md":"9ff60e38","api_service.md":"28946f2e","config_built-plugin.md":"9b035295","config_common.md":"ef8add40","guide_bot.md":"02213cca","guide_command.md":"c588d92b","guide_component.md":"d2abb193","guide_config.md":"9990ca7f","guide_deploy.md":"8a498116","guide_index.md":"9923d294","guide_prepare.md":"32c3c497","guide_repeater.md":"d67c880a","guide_start.md":"60d1a92f","index.md":"6e87687a","api_service-koa.md":"8994bd74","guide_prompt.md":"44f5d76e","config_adapter-onebot.md":"89101df5","api_service-router.md":"e539d155","guide_plugin.md":"2fa85982","api_zhin.md":"62d7e7b6","api_session.md":"be54baa4","config_adapter-icqq.md":"8f5eac0d"}
